scraper/__init__.py
scraper/__main__.py
scraper/author.py
scraper/books.py
scraper/shelves.py
scraper/user.py
goodreads_user_scraper-1.2.4.dist-info/AUTHORS
goodreads_user_scraper-1.2.4.dist-info/LICENSE.md
goodreads_user_scraper-1.2.4.dist-info/METADATA
goodreads_user_scraper-1.2.4.dist-info/WHEEL
goodreads_user_scraper-1.2.4.dist-info/entry_points.txt
goodreads_user_scraper-1.2.4.dist-info/top_level.txt
goodreads_user_scraper-1.2.4.dist-info/RECORD
