Metadata-Version: 2.1
Name: goodreads-user-scraper
Version: 1.2.4
Summary: Scrape user data from Goodreads
Author: Yash Totale
Author-email: totaleyash@gmail.com
License: MIT
Project-URL: Source Code, https://github.com/YashTotale/goodreads-user-scraper
Project-URL: Bug Tracker, https://github.com/YashTotale/goodreads-user-scraper/issues
Project-URL: Release Notes, https://github.com/YashTotale/goodreads-user-scraper/releases
Keywords: Goodreads,Web Scraper,CLI
Classifier: License :: OSI Approved :: MIT License
Classifier: Operating System :: OS Independent
Classifier: Programming Language :: Python :: 3
Classifier: Programming Language :: Python :: 3.7
License-File: LICENSE.md
License-File: AUTHORS
Requires-Dist: beautifulsoup4
